yapic_io/__init__.py
yapic_io/connector.py
yapic_io/coordinate_connector.py
yapic_io/dataset.py
yapic_io/minibatch.py
yapic_io/napari_connector.py
yapic_io/prediction_batch.py
yapic_io/tiff_connector.py
yapic_io/training_batch.py
yapic_io/transformations.py
yapic_io/utils.py
yapic_io-0.2.7.dist-info/LICENSE
yapic_io-0.2.7.dist-info/METADATA
yapic_io-0.2.7.dist-info/WHEEL
yapic_io-0.2.7.dist-info/top_level.txt
yapic_io-0.2.7.dist-info/RECORD
