Metadata-Version: 2.1
Name: yapic-io
Version: 0.2.7
Summary: io data handling module for various image sources as interface for pixel classification tools
Home-page: UNKNOWN
Author: Manuel Schoelling, Christoph Moehl
Author-email: manuel.schoelling@dzne.de, christoph.moehl@dzne.de
License: UNKNOWN
Platform: UNKNOWN
License-File: LICENSE
Requires-Dist: numpy (>=1.13.1)
Requires-Dist: munkres (>=1.0.8)
Requires-Dist: scikit-image (>=0.12.3)
Requires-Dist: tifffile
Requires-Dist: h5py
Requires-Dist: matplotlib
Requires-Dist: sparse (>=0.12.0)
